README.rst
ftdetect/__init__.py
ftdetect/cleanedges.py
ftdetect/example.py
ftdetect/features.py
ftdetect/masks.py
ftdetect/images/blocksTest.gif
ftdetect/images/house.png
ftdetect-1.0.1.dist-info/DESCRIPTION.rst
ftdetect-1.0.1.dist-info/METADATA
ftdetect-1.0.1.dist-info/RECORD
ftdetect-1.0.1.dist-info/WHEEL
ftdetect-1.0.1.dist-info/metadata.json
ftdetect-1.0.1.dist-info/top_level.txt
