Metadata-Version: 2.0
Name: ftdetect
Version: 1.0.1
Summary: An assortment of algorithms related to computer vision and image feature detection
Home-page: https://github.com/stachyra/ftdetect
Author: Andrew L. Stachyra
Author-email: andrewlstachyra@gmail.com
License: MIT
Platform: UNKNOWN
Classifier: Development Status :: 5 - Production/Stable
Classifier: Intended Audience :: Science/Research
Classifier: License :: OSI Approved :: MIT License
Classifier: Programming Language :: Python :: 2
Classifier: Programming Language :: Python :: 3
Classifier: Topic :: Scientific/Engineering :: Image Recognition
Requires-Dist: numpy
Requires-Dist: scipy
Requires-Dist: matplotlib
Requires-Dist: Pillow
